elastic_structlog/__init__.py
elastic_structlog/elastic_extension.py
elastic_structlog/elastic_processor.py
elastic_structlog/elastic_structlog_serializer.py
example/__init__.py
example/main.py
tests/__init__.py
tests/es_struct_log_test.py
tests/service_test.py
elastic_structlog-0.2.5.dist-info/METADATA
elastic_structlog-0.2.5.dist-info/WHEEL
elastic_structlog-0.2.5.dist-info/top_level.txt
elastic_structlog-0.2.5.dist-info/RECORD
