Metadata-Version: 2.2
Name: elastic_structlog
Version: 0.2.5
Summary: Extension / Wrapper for structlog library.
Author: Nuriel Gadilov
Author-email: nurielprivet@gmail.com
Keywords: python,structlog,es,elastic
Classifier: Development Status :: 3 - Alpha
Classifier: Intended Audience :: Education
Classifier: Programming Language :: Python :: 2
Classifier: Programming Language :: Python :: 3
Classifier: Operating System :: MacOS :: MacOS X
Classifier: Operating System :: Microsoft :: Windows
Requires-Dist: elasticsearch==8.17.0
Requires-Dist: structlog==24.4.0
Dynamic: author
Dynamic: author-email
Dynamic: classifier
Dynamic: description
Dynamic: description-content-type
Dynamic: keywords
Dynamic: requires-dist
Dynamic: summary
